hello/__init__.py
hello/hello.py
hello_czj-0.0.1.data/scripts/test_hello
hello_czj-0.0.1.dist-info/METADATA
hello_czj-0.0.1.dist-info/RECORD
hello_czj-0.0.1.dist-info/WHEEL
hello_czj-0.0.1.dist-info/top_level.txt
