Metadata-Version: 2.1
Name: hello-czj
Version: 0.0.1
Summary: This is a demo package for test.
Home-page: http://www.aidog.com
Author: czj
Author-email: kenneway@sina.com
License: UNKNOWN
Platform: UNKNOWN
